git_theta/__init__.py
git_theta/async_utils.py
git_theta/git_utils.py
git_theta/metadata.py
git_theta/params.py
git_theta/theta.py
git_theta/types.py
git_theta/utils.py
git_theta/checkpoints/__init__.py
git_theta/checkpoints/base.py
git_theta/checkpoints/flax_checkpoint.py
git_theta/checkpoints/pickled_dict_checkpoint.py
git_theta/checkpoints/safetensors_checkpoint.py
git_theta/checkpoints/tensorflow_checkpoint.py
git_theta/hooks/post-commit
git_theta/hooks/pre-push
git_theta/lsh/__init__.py
git_theta/lsh/base.py
git_theta/lsh/euclidean_lsh.py
git_theta/lsh/pool.py
git_theta/lsh/types.py
git_theta/merges/__init__.py
git_theta/merges/average.py
git_theta/merges/base.py
git_theta/merges/context.py
git_theta/merges/take.py
git_theta/scripts/__init__.py
git_theta/scripts/git_theta.py
git_theta/scripts/git_theta_diff.py
git_theta/scripts/git_theta_filter.py
git_theta/scripts/git_theta_merge.py
git_theta/updates/__init__.py
git_theta/updates/base.py
git_theta/updates/dense.py
git_theta/updates/ia3.py
git_theta/updates/low_rank.py
git_theta/updates/sparse.py
git_theta-0.2.0.dist-info/LICENSE.md
git_theta-0.2.0.dist-info/METADATA
git_theta-0.2.0.dist-info/WHEEL
git_theta-0.2.0.dist-info/entry_points.txt
git_theta-0.2.0.dist-info/top_level.txt
git_theta-0.2.0.dist-info/RECORD
