Metadata-Version: 2.1
Name: git-theta
Version: 0.2.0
Summary: Version control system for machine learning model checkpoints.
Home-page: https://github.com/r-three/git-theta
Author: Colin Raffel
Author-email: craffel@gmail.com
License: MIT
Keywords: git vcs machine-learning
Classifier: License :: OSI Approved :: MIT License
Classifier: Programming Language :: Python
Classifier: Development Status :: 4 - Beta
Classifier: Environment :: Console
Classifier: Intended Audience :: Developers
Classifier: Intended Audience :: Science/Research
Classifier: Intended Audience :: Developers
Classifier: Topic :: Software Development :: Version Control
Classifier: Topic :: Scientific/Engineering :: Artificial Intelligence
Classifier: Programming Language :: Python :: 3 :: Only
Classifier: Natural Language :: English
Classifier: Operating System :: MacOS :: MacOS X
Classifier: Operating System :: Microsoft :: Windows
Classifier: Operating System :: POSIX :: Linux
Requires-Python: >=3.8
License-File: LICENSE.md
Requires-Dist: GitPython
Requires-Dist: tensorstore (>=0.1.14)
Requires-Dist: file-or-name
Requires-Dist: six
Requires-Dist: scipy
Requires-Dist: numba
Requires-Dist: msgpack
Requires-Dist: importlib-metadata ; python_version < "3.10.0"
Requires-Dist: typing-extensions ; python_version < "3.8.0"
Requires-Dist: importlib-resources ; python_version < "3.9.0"
Provides-Extra: all
Requires-Dist: tensorflow ; extra == 'all'
Requires-Dist: safetensors ; extra == 'all'
Requires-Dist: torch ; extra == 'all'
Requires-Dist: flax ; extra == 'all'
Provides-Extra: docs
Requires-Dist: sphinx ; extra == 'docs'
Requires-Dist: numpydoc ; extra == 'docs'
Provides-Extra: flax
Requires-Dist: flax ; extra == 'flax'
Provides-Extra: pytorch
Requires-Dist: torch ; extra == 'pytorch'
Provides-Extra: safetensors
Requires-Dist: safetensors ; extra == 'safetensors'
Provides-Extra: tensorflow
Requires-Dist: tensorflow ; extra == 'tensorflow'
Provides-Extra: test
Requires-Dist: pytest ; extra == 'test'
